{"id":"OP01-029_p2","pack_id":"622301","name":"Radical Beam !!","rarity":"Uncommon","category":"Event","img_url":"../images/cardlist/card/OP01-029_p2.webp?251024","img_full_url":"https://fr.onepiece-cardgame.com/images/cardlist/card/OP01-029_p2.webp?251024","colors":["Red"],"cost":1,"attributes":[],"power":null,"counter":null,"types":["Équipage de Chapeau de paille"],"effect":"[Contre] Jusqu'à 1 de vos Leaders ou Personnages gagne +2000 de puissance pour tout le combat. Puis, si vous avez 2 cartes ou moins dans votre Vie, il gagne de nouveau +2000 de puissance pour tout le combat.","trigger":"[Déclenchement] Jusqu'à 1 de vos Leaders ou Personnages gagne +1000 de puissance pour tout le tour."}