{"id":"OP06-003_p1","pack_id":"622301","name":"Emporio Ivankov","rarity":"Uncommon","category":"Character","img_url":"../images/cardlist/card/OP06-003_p1.webp?251024","img_full_url":"https://fr.onepiece-cardgame.com/images/cardlist/card/OP06-003_p1.webp?251024","colors":["Red"],"cost":5,"attributes":["Special"],"power":6000,"counter":null,"types":["Armée révolutionnaire"],"effect":"[Jouée] Regardez 3 cartes du dessus de votre deck et jouez jusqu'à 1 carte Personnage de type {Armée révolutionnaire} ayant 5000 de puissance ou moins. Puis, placez les cartes restantes au-dessous de votre deck dans l'ordre de votre choix.","trigger":null}