{"id":"OP12-109","pack_id":"563112","name":"Pacifista","rarity":"Common","category":"Character","img_url":"../images/cardlist/card/OP12-109.png?251024","img_full_url":"https://asia-th.onepiece-cardgame.com/images/cardlist/card/OP12-109.png?251024","colors":["Yellow"],"cost":4,"attributes":["Special"],"power":5000,"counter":1000,"types":["อาวุธชีวภาพ","เอ็กเฮด","กองทัพเรือ"],"effect":"-","trigger":"[ทริกเกอร์] ทำการ KO คาแรกเตอร์ของคู่แข่ง ที่มีคอสต์ 1 หรือต่ำกว่า, จำนวนไม่เกิน 1 ใบ, และนำการ์ดใบนี้ ขึ้นมือ."}