{"id":"OP12-074","pack_id":"563112","name":"Patty","rarity":"Common","category":"Character","img_url":"../images/cardlist/card/OP12-074.png?251024","img_full_url":"https://asia-th.onepiece-cardgame.com/images/cardlist/card/OP12-074.png?251024","colors":["Purple"],"cost":3,"attributes":["Slash"],"power":2000,"counter":2000,"types":["อีสต์บลู"],"effect":"[เมื่อลงสนาม] สามารถทิ้ง อีเวนต์ จากบนมือของเรา จำนวน 1 ใบ : ถ้าลีดเดอร์ของเราคือ [Sanji] ละก็, จะได้นำ ด้ง!! จากด้ง!! เด็ค จำนวนไม่เกิน 1 ใบ, มาวางเพิ่มแบบ แอ็คทีฟ.","trigger":null}