{"id":"OP10-110","pack_id":"622110","name":"Heat et Wire","rarity":"Common","category":"Character","img_url":"../images/cardlist/card/OP10-110.webp?251024","img_full_url":"https://fr.onepiece-cardgame.com/images/cardlist/card/OP10-110.webp?251024","colors":["Yellow"],"cost":3,"attributes":["Slash","Special"],"power":4000,"counter":1000,"types":["Équipage de Kidd"],"effect":"[Jouée] Épuisez jusqu'à 1 Personnage adverse ayant un coût inférieur ou égal au nombre de cartes dans la Vie adverse.","trigger":"[Déclenchement] Si vous avez 2 cartes ou moins dans votre Vie, jouez cette carte."}