{"id":"OP10-041","pack_id":"622110","name":"Radio Knife","rarity":"Rare","category":"Event","img_url":"../images/cardlist/card/OP10-041.webp?251024","img_full_url":"https://fr.onepiece-cardgame.com/images/cardlist/card/OP10-041.webp?251024","colors":["Green"],"cost":4,"attributes":[],"power":null,"counter":null,"types":["Dressrosa","Supernovae","Équipage du Heart"],"effect":"[Principale] Épuisez jusqu'à 1 Personnage adverse ayant un coût de 6 ou moins. Puis, mettez KO jusqu'à 1 Personnage adverse épuisé ayant un coût de 5 ou moins.","trigger":"[Déclenchement] Épuisez jusqu'à 1 Personnage adverse ayant un coût de 4 ou moins."}