{"id":"EB02-026_p1","pack_id":"622202","name":"Nefertari Vivi","rarity":"SuperRare","category":"Character","img_url":"../images/cardlist/card/EB02-026_p1.webp?251024","img_full_url":"https://fr.onepiece-cardgame.com/images/cardlist/card/EB02-026_p1.webp?251024","colors":["Blue"],"cost":3,"attributes":["Slash"],"power":2000,"counter":1000,"types":["Royaume d'Alabasta"],"effect":"[Jouée] Si votre Leader est multicolore et que vous avez 5 cartes ou moins dans votre main, piochez 2 cartes.","trigger":null}