{"id":"ST21-017","pack_id":"563021","name":"Gum-Gum Mole Pistol","rarity":"Common","category":"Event","img_url":"../images/cardlist/card/ST21-017.png?251024","img_full_url":"https://asia-th.onepiece-cardgame.com/images/cardlist/card/ST21-017.png?251024","colors":["Red"],"cost":4,"attributes":[],"power":null,"counter":null,"types":["สี่จักรพรรดิ","กลุ่มหมวกฟาง"],"effect":"[เมน] ในเทิร์นนี้, คาแรกเตอร์ของคู่แข่ง จำนวนไม่เกิน 1 ใบ, จะมีพาวเวอร์ -5000. จากนั้น, ถ้าเรามีคาแรกเตอร์ ที่มีพาวเวอร์ 6000 หรือสูงกว่า อยู่ด้วยละก็, ทำการ KO คาแรกเตอร์ของคู่แข่ง ที่มีพาวเวอร์ 2000 หรือต่ำกว่า, จำนวนไม่เกิน 1 ใบ.","trigger":"[ทริกเกอร์] ใช้งานความสามารถ [เมน] ของการ์ดใบนี้."}