[{"id":"OP01-016_p3","pack_id":"563010","name":"Nami (Parallel)","rarity":"Rare","category":"Character","img_url":"../images/cardlist/card/OP01-016_p3.png?251024","img_full_url":"https://asia-th.onepiece-cardgame.com/images/cardlist/card/OP01-016_p3.png?251024","colors":["Red"],"cost":1,"attributes":["Special"],"power":2000,"counter":1000,"types":["กลุ่มโจรสลัดหมวกฟาง"],"effect":"[เมื่อลงสนาม] ดูการ์ดจากข้างบนเด็คของเรา จำนวน 5 ใบ, และนำการ์ดที่มีคุณสมบัติ &lt; กลุ่มโจรสลัดหมวกฟาง &gt; นอกเหนือจาก [Nami] จำนวนไม่เกิน 1 ใบ มาแสดงให้ดู, แล้วนำขึ้นมือ. จากนั้น, นำการ์ดที่เหลือไปวางในลำดับใดก็ได้ ที่ข้างใต้เด็ค.","trigger":null},{"id":"OP01-025_p2","pack_id":"563010","name":"Roronoa Zoro (Parallel)","rarity":"SuperRare","category":"Character","img_url":"../images/cardlist/card/OP01-025_p2.png?251024","img_full_url":"https://asia-th.onepiece-cardgame.com/images/cardlist/card/OP01-025_p2.png?251024","colors":["Red"],"cost":3,"attributes":["Slash"],"power":5000,"counter":null,"types":["ซูเปอร์โนวา","กลุ่มโจรสลัดหมวกฟาง"],"effect":"[จู่โจมฉับพลัน] (การ์ดใบนี้สามารถโจมตีในเทิร์นที่เพิ่งลงสนามได้).","trigger":null},{"id":"ST10-001","pack_id":"563010","name":"Trafalgar Law","rarity":"Leader","category":"Leader","img_url":"../images/cardlist/card/ST10-001.png?251024","img_full_url":"https://asia-th.onepiece-cardgame.com/images/cardlist/card/ST10-001.png?251024","colors":["Red","Purple"],"cost":4,"attributes":["Slash"],"power":5000,"counter":null,"types":["กลุ่มโจรสลัดฮาร์ท"],"effect":"[ใช้งาน : เมน] [เทิร์นละ 1 ครั้ง] ด้ง!! - 3 (สามารถนำ ด้ง!! ในสนามของเรากลับด้ง!! เด็ค ตามจำนวนที่ระบุ) : นำคาแรกเตอร์ของคู่แข่ง ที่มีพาวเวอร์ 3000 หรือต่ำกว่า จำนวนไม่เกิน 1 ใบ ไปวางที่ข้างใต้เด็คของเจ้าของ, และนำคาแรกเตอร์การ์ด ที่มีคอสต์ 4 หรือต่ำกว่า จากบนมือของเรา จำนวนไม่เกิน 1 ใบ, ลงสนาม.","trigger":null},{"id":"ST10-002","pack_id":"563010","name":"Monkey.D.Luffy","rarity":"Leader","category":"Leader","img_url":"../images/cardlist/card/ST10-002.png?251024","img_full_url":"https://asia-th.onepiece-cardgame.com/images/cardlist/card/ST10-002.png?251024","colors":["Red","Purple"],"cost":3,"attributes":["Strike"],"power":6000,"counter":null,"types":["กลุ่มหมวกฟาง"],"effect":"[ใช้งาน : เมน] [เทิร์นละ 1 ครั้ง] ถ้าในสนามของเรามี ด้ง!! อยู่ 0 ใบ, หรือว่า ถ้าในสนามของเรามี ด้ง!! อยู่จำนวน 8 ใบ หรือมากกว่า, จะนำ ด้ง!! จากด้ง!! เด็ค ของเรา จำนวนไม่เกิน 1 ใบ มาวางเพิ่มแบบ แอ็คทีฟ.","trigger":null},{"id":"ST10-003","pack_id":"563010","name":"Eustass\"Captain\"Kid","rarity":"Leader","category":"Leader","img_url":"../images/cardlist/card/ST10-003.png?251024","img_full_url":"https://asia-th.onepiece-cardgame.com/images/cardlist/card/ST10-003.png?251024","colors":["Red","Purple"],"cost":5,"attributes":["Special"],"power":5000,"counter":null,"types":["กลุ่มโจรสลัดคิด"],"effect":"[เทิร์นตัวเอง] ถ้าเรามี ไลฟ์ จำนวน 4 ใบ หรือมากกว่า, ลีดเดอร์นี้ จะมีพาวเวอร์ -1000.<br>[เมื่อโจมตี] ด้ง!! - 1 (สามารถนำ ด้ง!! ในสนามของเรากลับด้ง!! เด็ค ตามจำนวนที่ระบุ) : ในเทิร์นนี้, ลีดเดอร์นี้, จะมีพาวเวอร์ +2000.","trigger":null},{"id":"ST10-004","pack_id":"563010","name":"Sanji","rarity":"Common","category":"Character","img_url":"../images/cardlist/card/ST10-004.png?251024","img_full_url":"https://asia-th.onepiece-cardgame.com/images/cardlist/card/ST10-004.png?251024","colors":["Red"],"cost":6,"attributes":["Strike"],"power":6000,"counter":1000,"types":["กลุ่มหมวกฟาง"],"effect":"[เมื่อลงสนาม] ถ้าคู่แข่งมีคาแรคเตอร์ ที่มีพาวเวอร์ 5000 หรือมากกว่า อยู่ด้วย, ในเทิร์นนี้, คาแรกเตอร์นี้ จะได้รับ [จู่โจมฉับพลัน].<br>(การ์ดใบนี้สามารถโจมตีในเทิร์นที่เพิ่งลงสนามได้)","trigger":null},{"id":"ST10-005","pack_id":"563010","name":"Jinbe","rarity":"Common","category":"Character","img_url":"../images/cardlist/card/ST10-005.png?251024","img_full_url":"https://asia-th.onepiece-cardgame.com/images/cardlist/card/ST10-005.png?251024","colors":["Red"],"cost":2,"attributes":["Strike"],"power":2000,"counter":2000,"types":["เผ่ามนุษย์เงือก","กลุ่มหมวกฟาง"],"effect":"[ด้ง!! x 1] [เมื่อโจมตี] ในเทิร์นนี้ คาแรกเตอร์ ของคู่แข่ง จำนวนไม่เกิน 1 ใบ, จะมีพาวเวอร์ –2000.","trigger":null},{"id":"ST10-006","pack_id":"563010","name":"Monkey.D.Luffy","rarity":"SuperRare","category":"Character","img_url":"../images/cardlist/card/ST10-006.png?251024","img_full_url":"https://asia-th.onepiece-cardgame.com/images/cardlist/card/ST10-006.png?251024","colors":["Red"],"cost":10,"attributes":["Strike"],"power":11000,"counter":null,"types":["กลุ่มหมวกฟาง"],"effect":"[จู่โจมฉับพลัน] (การ์ดใบนี้สามารถโจมตีในเทิร์นที่เพิ่งลงสนามได้)<br>[เทิร์นละ 1 ครั้ง] ตอนที่คู่แข่งใช้งาน [บล็อกเกอร์], จะทำการ KO คาแรกเตอร์ของคู่แข่ง ที่มีพาวเวอร์ 8000 หรือต่ำกว่า จำนวนไม่เกิน 1 ใบ.","trigger":null},{"id":"ST10-007","pack_id":"563010","name":"Killer","rarity":"Common","category":"Character","img_url":"../images/cardlist/card/ST10-007.png?251024","img_full_url":"https://asia-th.onepiece-cardgame.com/images/cardlist/card/ST10-007.png?251024","colors":["Purple"],"cost":5,"attributes":["Slash"],"power":6000,"counter":1000,"types":["กลุ่มโจรสลัดคิด"],"effect":"[เทิร์นตัวเอง] [เทิร์นละ 1 ครั้ง] เมื่อมี ด้ง!! ในสนามของเรา ถูกนำกลับ ด้ง!! เด็ค, จะทำการ KO คาแรกเตอร์ของคู่แข่ง ที่มีคอสต์ 3 หรือต่ำกว่า ที่กำลังเรสต์อยู่ จำนวนไม่เกิน 1 ใบ.","trigger":null},{"id":"ST10-008","pack_id":"563010","name":"Shachi &amp; Penguin","rarity":"Common","category":"Character","img_url":"../images/cardlist/card/ST10-008.png?251024","img_full_url":"https://asia-th.onepiece-cardgame.com/images/cardlist/card/ST10-008.png?251024","colors":["Purple"],"cost":4,"attributes":["Ranged"],"power":5000,"counter":2000,"types":["กลุ่มโจรสลัดฮาร์ท"],"effect":"[เมื่อลงสนาม] ถ้าในสนามของเรามี ด้ง!! อยู่จำนวน 3 ใบ หรือน้อยกว่า, จะนำ ด้ง!! จากด้ง!! เด็ค จำนวนไม่เกิน 2 ใบ, มาวางเพิ่มแบบ เรสต์.","trigger":null},{"id":"ST10-009","pack_id":"563010","name":"Jean Bart","rarity":"Common","category":"Character","img_url":"../images/cardlist/card/ST10-009.png?251024","img_full_url":"https://asia-th.onepiece-cardgame.com/images/cardlist/card/ST10-009.png?251024","colors":["Purple"],"cost":4,"attributes":["Strike"],"power":5000,"counter":1000,"types":["กลุ่มโจรสลัดฮาร์ท"],"effect":"[เมื่อลงสนาม] (1) (สามารถ เรสต์ ด้ง!! ในคอสต์แอเรียตามจำนวนที่ระบุ) : นำ ด้ง!! จากด้ง!! เด็ค จำนวนไม่เกิน 1 ใบ, มาวางเพิ่มแบบ แอ็คทีฟ.","trigger":null},{"id":"ST10-010","pack_id":"563010","name":"Trafalgar Law","rarity":"SuperRare","category":"Character","img_url":"../images/cardlist/card/ST10-010.png?251024","img_full_url":"https://asia-th.onepiece-cardgame.com/images/cardlist/card/ST10-010.png?251024","colors":["Purple"],"cost":4,"attributes":["Slash"],"power":5000,"counter":1000,"types":["กลุ่มโจรสลัดฮาร์ท"],"effect":"[บล็อกเกอร์] (ขณะที่คู่แข่งโจมตี, จะสามารถ เรสต์ การ์ดใบนี้, และเปลี่ยนเป้าหมายการโจมตีมาที่การ์ดใบนี้)<br>[เมื่อลงสนาม] ด้ง!! - 1 (สามารถนำ ด้ง!! ในสนามของเรากลับ ด้ง!! เด็ค ตามจำนวนที่ระบุ) : ถ้าคู่แข่งมีการ์ดบนมืออยู่ จำนวน 7 ใบ หรือมากกว่า, จะทิ้งการ์ดบนมือของคู่แข่ง จำนวน 2 ใบ.","trigger":null},{"id":"ST10-011","pack_id":"563010","name":"Heat","rarity":"Common","category":"Character","img_url":"../images/cardlist/card/ST10-011.png?251024","img_full_url":"https://asia-th.onepiece-cardgame.com/images/cardlist/card/ST10-011.png?251024","colors":["Purple"],"cost":3,"attributes":["Special"],"power":4000,"counter":1000,"types":["กลุ่มโจรสลัดคิด"],"effect":"[เทิร์นตัวเอง] [เทิร์นละ 1 ครั้ง] เมื่อมี ด้ง!! ในสนามของเรา ถูกนำกลับ ด้ง!! เด็ค, จนกระทั่งถึงช่วงเริ่มต้นเทิร์นของเราในครั้งถัดไป, คาแรกเตอร์นี้, จะมีพาวเวอร์ +2000.","trigger":null},{"id":"ST10-012","pack_id":"563010","name":"Bepo","rarity":"Common","category":"Character","img_url":"../images/cardlist/card/ST10-012.png?251024","img_full_url":"https://asia-th.onepiece-cardgame.com/images/cardlist/card/ST10-012.png?251024","colors":["Purple"],"cost":4,"attributes":["Strike"],"power":5000,"counter":1000,"types":["เผ่ามิงค์","กลุ่มโจรสลัดฮาร์ท"],"effect":"[เมื่อลงสนาม] / [เมื่อโจมตี] ถ้าจำนวน ด้ง!! ที่อยู่บนสนามของคู่แข่ง มีมากกว่าจำนวน ด้ง!! ที่อยู่บนสนามของเรา, จะนำ ด้ง!! จากด้ง!! เด็ค จำนวนไม่เกิน 1 ใบ, มาวางเพิ่มแบบ เรสต์.","trigger":null},{"id":"ST10-013","pack_id":"563010","name":"Eustass\"Captain\"Kid","rarity":"SuperRare","category":"Character","img_url":"../images/cardlist/card/ST10-013.png?251024","img_full_url":"https://asia-th.onepiece-cardgame.com/images/cardlist/card/ST10-013.png?251024","colors":["Purple"],"cost":7,"attributes":["Special"],"power":8000,"counter":null,"types":["กลุ่มโจรสลัดคิด"],"effect":"[เมื่อลงสนาม] / [เมื่อโจมตี] ด้ง!! - 1 (สามารถนำ ด้ง!! ในสนามของเรากลับ ด้ง!! เด็ค ตามจำนวนที่ระบุ) : จนกระทั่งถึงช่วงเริ่มต้นเทิร์นของเราในครั้งถัดไป, ลีดเดอร์ ของเรา จำนวนไม่เกิน 1 ใบ, จะมีพาวเวอร์ +1000.","trigger":null},{"id":"ST10-014","pack_id":"563010","name":"Wire","rarity":"Common","category":"Character","img_url":"../images/cardlist/card/ST10-014.png?251024","img_full_url":"https://asia-th.onepiece-cardgame.com/images/cardlist/card/ST10-014.png?251024","colors":["Purple"],"cost":3,"attributes":["Slash"],"power":3000,"counter":1000,"types":["กลุ่มโจรสลัดคิด"],"effect":"[บล็อกเกอร์] (ขณะที่คู่แข่งโจมตี, จะสามารถ เรสต์ การ์ดใบนี้, และเปลี่ยนเป้าหมายการโจมตีมาที่การ์ดใบนี้)<br>[เทิร์นละ 1 ครั้ง] เมื่อมี ด้ง!! ในสนามของเรา ถูกนำกลับ ด้ง!! เด็ค, จะจั่วการ์ด จำนวน 1 ใบ, และทิ้งการ์ดบนมือ จำนวน 1 ใบ.","trigger":null},{"id":"ST10-015","pack_id":"563010","name":"Gum-Gum Giant Sumo Slap","rarity":"Common","category":"Event","img_url":"../images/cardlist/card/ST10-015.png?251024","img_full_url":"https://asia-th.onepiece-cardgame.com/images/cardlist/card/ST10-015.png?251024","colors":["Red"],"cost":1,"attributes":[],"power":null,"counter":null,"types":["กลุ่มหมวกฟาง"],"effect":"[เคาน์เตอร์] ในแบทเทิลนี้, ลีดเดอร์ หรือ คาแรกเตอร์ ของเรา จำนวนไม่เกิน 1 ใบ, จะมีพาวเวอร์ +2000, และทำการ KO คาแรกเตอร์ของคู่แข่ง ที่มีพาวเวอร์ 2000 หรือต่ำกว่า จำนวนไม่เกิน 1 ใบ.","trigger":null},{"id":"ST10-016","pack_id":"563010","name":"Gum-Gum Kong Gatling","rarity":"Common","category":"Event","img_url":"../images/cardlist/card/ST10-016.png?251024","img_full_url":"https://asia-th.onepiece-cardgame.com/images/cardlist/card/ST10-016.png?251024","colors":["Red"],"cost":5,"attributes":[],"power":null,"counter":null,"types":["กลุ่มหมวกฟาง"],"effect":"[เมน] ทำการ KO คาแรกเตอร์ของคู่แข่ง ที่มีพาวเวอร์ 7000 หรือต่ำกว่า จำนวนไม่เกิน 1 ใบ.","trigger":"[ทริกเกอร์] จนกระทั่งถึงตอนจบเทิร์นของเราในครั้งถัดไป, ลีดเดอร์ ของเรา จำนวนไม่เกิน 1 ใบ, จะมีพาวเวอร์ +1000."},{"id":"ST10-017","pack_id":"563010","name":"Punk Vise","rarity":"Common","category":"Event","img_url":"../images/cardlist/card/ST10-017.png?251024","img_full_url":"https://asia-th.onepiece-cardgame.com/images/cardlist/card/ST10-017.png?251024","colors":["Purple"],"cost":3,"attributes":[],"power":null,"counter":null,"types":["กลุ่มโจรสลัดคิด"],"effect":"[เมน] ทำการ เรสต์ คาแรกเตอร์ของคู่แข่ง ที่มีคอสต์ 2 หรือต่ำกว่า จำนวนไม่เกิน 1 ใบ, และนำ ด้ง!! จากด้ง!! เด็ค จำนวนไม่เกิน 1 ใบ, มาวางเพิ่มแบบ เรสต์.","trigger":"[ทริกเกอร์] นำ ด้ง!! จากด้ง!! เด็ค จำนวนไม่เกิน 1 ใบ, มาวางเพิ่มแบบ แอ็คทีฟ."}]