{"id":"OP01-049","pack_id":"563101","name":"Bepo","rarity":"Rare","category":"Character","img_url":"../images/cardlist/card/OP01-049.png?251024","img_full_url":"https://asia-th.onepiece-cardgame.com/images/cardlist/card/OP01-049.png?251024","colors":["Green"],"cost":4,"attributes":["Strike"],"power":4000,"counter":2000,"types":["เผ่ามิงค์","กลุ่มโจรสลัดฮาร์ท"],"effect":"[ด้ง!! x 1] [เมื่อโจมตี] นำคาแรกเตอร์การ์ด ที่มีคอสต์ 4 หรือต่ำกว่า ที่มีคุณสมบัติ &lt; กลุ่มโจรสลัดฮาร์ท &gt; นอกเหนือจาก [Bepo] จากบนมือของเรา จำนวนไม่เกิน 1 ใบ, ลงสนาม.","trigger":null}