{"id":"OP11-025","pack_id":"622111","name":"Ishilly","rarity":"Common","category":"Character","img_url":"../images/cardlist/card/OP11-025.webp?251024","img_full_url":"https://fr.onepiece-cardgame.com/images/cardlist/card/OP11-025.webp?251024","colors":["Green"],"cost":2,"attributes":["Wisdom"],"power":null,"counter":1000,"types":["ODYSSEY","Sept grands corsaires"],"effect":"[Attaque adverse] [Une fois par tour] Vous pouvez épuiser 1 de vos cartes DON!! et ce Personnage&nbsp;: Jusqu'à 1 de vos Leaders ou Personnages gagne +1000 de puissance pour tout le combat.","trigger":null}