{"id":"P-070_r1","pack_id":"622302","name":"Carrot","rarity":"Promo","category":"Character","img_url":"../images/cardlist/card/P-070_r1.webp?251024","img_full_url":"https://fr.onepiece-cardgame.com/images/cardlist/card/P-070_r1.webp?251024","colors":["Green"],"cost":2,"attributes":["Special"],"power":2000,"counter":1000,"types":["Minks"],"effect":"[Bloqueur] (Après que votre adversaire a déclaré une attaque, vous pouvez épuiser cette carte pour qu'elle devienne la cible de l'attaque.)","trigger":null}