{"id":"PRB02-009_p1","pack_id":"622302","name":"Mr 3(Galdino)","rarity":"Rare","category":"Character","img_url":"../images/cardlist/card/PRB02-009_p1.webp?251024","img_full_url":"https://fr.onepiece-cardgame.com/images/cardlist/card/PRB02-009_p1.webp?251024","colors":["Blue"],"cost":2,"attributes":["Special"],"power":1000,"counter":1000,"types":["Cross Guild","Ex-Baroque Works"],"effect":"Peut être activé quand ce Personnage est épuisé par un effet adverse. Vous pouvez placer ce Personnage dans votre Défausse et piocher 2 cartes.<br>[Bloqueur]","trigger":null}