{"id":"OP09-004_p4","pack_id":"622113","name":"Shanks","rarity":"Special","category":"Character","img_url":"../images/cardlist/card/OP09-004_p4.webp?251024","img_full_url":"https://fr.onepiece-cardgame.com/images/cardlist/card/OP09-004_p4.webp?251024","colors":["Red"],"cost":10,"attributes":["Slash"],"power":12000,"counter":null,"types":["Quatre Empereurs","Équipage du Roux"],"effect":"Tous les Personnages adverses perdent -1000 de puissance.<br>[Initiative] (Cette carte peut attaquer durant le tour où elle est jouée.)<br>","trigger":null}