{"id":"OP13-093","pack_id":"622113","name":"Morgans","rarity":"Common","category":"Character","img_url":"../images/cardlist/card/OP13-093.webp?251024","img_full_url":"https://fr.onepiece-cardgame.com/images/cardlist/card/OP13-093.webp?251024","colors":["Black"],"cost":3,"attributes":["Wisdom"],"power":4000,"counter":1000,"types":["Journaliste"],"effect":"[Bloqueur] (Après que votre adversaire a déclaré une attaque, vous pouvez épuiser cette carte pour qu'elle devienne la cible de l'attaque.)<br>[Jouée] Piochez 2 cartes et défaussez 2 cartes de votre main.","trigger":null}