{"id":"OP06-115_p1","pack_id":"622901","name":"C'est toi qui vas nous faire le plaisir de disparaître","rarity":"Rare","category":"Event","img_url":"../images/cardlist/card/OP06-115_p1.webp?251024","img_full_url":"https://fr.onepiece-cardgame.com/images/cardlist/card/OP06-115_p1.webp?251024","colors":["Yellow"],"cost":null,"attributes":[],"power":null,"counter":null,"types":["Île céleste"],"effect":"[Contre] Vous pouvez défausser 1 carte de votre main&nbsp;: Jusqu'à 1 de vos Leaders ou Personnages gagne +3000 de puissance pour tout le combat.","trigger":"[Déclenchement] Si vous avez 0 carte dans votre Vie, ajoutez au-dessus de votre Vie jusqu'à 1 carte du dessus de votre deck. Puis, défaussez 1 carte de votre main."}